pardesichat/__init__.py
pardesichat/pardesichat.py
pardesichat-1.1.0.dist-info/licenses/NOTICE.md
pardesichat-1.1.0.dist-info/METADATA
pardesichat-1.1.0.dist-info/WHEEL
pardesichat-1.1.0.dist-info/entry_points.txt
pardesichat-1.1.0.dist-info/top_level.txt
pardesichat-1.1.0.dist-info/RECORD
