Metadata-Version: 2.4
Name: pardesichat
Version: 1.1.0
Summary: A terminal-based chat application with mulitplayer games and an on-device AI assistant
Author-email: Arsalan Pardesi <arsalanpardesi.ai@gmail.com>
License: MIT License
Project-URL: Homepage, https://github.com/arsalanpardesi/pardesichat
Project-URL: Bug Tracker, https://github.com/arsalanpardesi/pardesichat/issues
Classifier: Programming Language :: Python :: 3
Classifier: Operating System :: OS Independent
Classifier: Environment :: Console
Classifier: Topic :: Communications :: Chat
Requires-Python: >=3.8
License-File: NOTICE.md
Requires-Dist: requests
Requires-Dist: Pillow
Requires-Dist: newspaper3k
Requires-Dist: ollama
Requires-Dist: lxml_html_clean
Dynamic: license-file
